{"imagePath":"silingfazhengti_tex.png","width":512,"height":512,"name":"silingfazhengti","SubTexture":[{"width":32,"y":224,"height":46,"name":"死灵法_切图/PPP111","x":475},{"width":10,"y":178,"height":9,"name":"死灵法_切图/L_111","x":303},{"width":8,"y":232,"height":8,"name":"死灵法_切图/L_hand","x":388},{"width":42,"y":190,"height":40,"name":"死灵法_切图/T111","x":360},{"width":6,"y":389,"height":10,"name":"死灵法_切图/L_222","x":448},{"width":1,"y":149,"height":1,"name":"死灵法_切图/Body222","x":311},{"width":25,"y":272,"height":19,"name":"死灵法_切图/Body","x":475},{"width":7,"y":232,"height":13,"name":"死灵法_切图/Body111","x":379},{"width":17,"y":232,"height":11,"name":"死灵法_切图/xiongqiang","x":360},{"width":31,"y":364,"height":25,"name":"死灵法_切图/Legs","x":404},{"width":38,"y":247,"height":52,"name":"死灵法_切图/Head","x":358},{"width":9,"y":162,"height":14,"name":"死灵法_切图/R_111","x":303},{"width":13,"y":364,"height":11,"name":"死灵法_切图/R_222","x":457},{"width":27,"y":295,"height":81,"name":"死灵法_切图/F111","x":473},{"width":18,"y":364,"height":23,"name":"死灵法_切图/F222","x":437},{"width":6,"y":137,"height":23,"name":"死灵法_切图/F333","x":303},{"width":4,"y":301,"height":6,"name":"死灵法_切图/F444","x":365},{"width":9,"y":389,"height":8,"name":"死灵法_切图/R_hand","x":437},{"width":1,"y":143,"height":1,"name":"skill-t0009","x":311},{"width":1,"y":304,"height":1,"name":"skill-t0007","x":371},{"width":1,"y":140,"height":1,"name":"skill-t0004","x":311},{"width":1,"y":238,"height":1,"name":"skill-t0001","x":398},{"width":1,"y":242,"height":1,"name":"skill-t0005","x":388},{"width":1,"y":242,"height":1,"name":"skill-t0008","x":397},{"width":1,"y":232,"height":1,"name":"skill-t0003","x":401},{"width":1,"y":137,"height":1,"name":"skill-t0002","x":311},{"width":1,"y":307,"height":1,"name":"skill-t0006","x":371},{"width":1,"y":301,"height":1,"name":"skill2-t0033","x":377},{"width":1,"y":307,"height":1,"name":"skill2-t0031","x":374},{"width":1,"y":241,"height":1,"name":"skill2-t0027","x":400},{"width":1,"y":152,"height":1,"name":"skill2-t0023","x":311},{"width":1,"y":304,"height":1,"name":"skill2-t0019","x":374},{"width":1,"y":235,"height":1,"name":"skill2-t0022","x":398},{"width":1,"y":244,"height":1,"name":"skill2-t0026","x":400},{"width":1,"y":242,"height":1,"name":"skill2-t0030","x":394},{"width":1,"y":232,"height":1,"name":"skill2-t0034","x":398},{"width":1,"y":158,"height":1,"name":"skill2-t0035","x":311},{"width":1,"y":146,"height":1,"name":"skill2-t0032","x":311},{"width":1,"y":301,"height":1,"name":"skill2-t0028","x":374},{"width":1,"y":242,"height":1,"name":"skill2-t0024","x":391},{"width":1,"y":301,"height":1,"name":"skill2-t0020","x":371},{"width":1,"y":155,"height":1,"name":"skill2-t0021","x":311},{"width":1,"y":238,"height":1,"name":"skill2-t0025","x":401},{"width":1,"y":235,"height":1,"name":"skill2-t0029","x":401},{"frameY":-32,"y":137,"frameWidth":112,"frameHeight":112,"width":55,"height":55,"name":"attack000007","frameX":-30,"x":246},{"frameY":-31,"y":1,"frameWidth":112,"frameHeight":112,"width":57,"height":57,"name":"attack000008","frameX":-29,"x":333},{"frameY":-28,"y":68,"frameWidth":112,"frameHeight":112,"width":62,"height":62,"name":"attack000009","frameX":-26,"x":316},{"frameY":-26,"y":295,"frameWidth":112,"frameHeight":112,"width":67,"height":67,"name":"attack000010","frameX":-24,"x":404},{"frameY":-23,"y":76,"frameWidth":112,"frameHeight":112,"width":73,"height":73,"name":"attack000011","frameX":-21,"x":404},{"frameY":-20,"y":401,"frameWidth":112,"frameHeight":112,"width":78,"height":78,"name":"attack000012","frameX":-18,"x":416},{"frameY":-22,"y":310,"frameWidth":112,"frameHeight":112,"width":74,"height":74,"name":"attack000013","frameX":-20,"x":328},{"frameY":-19,"y":401,"frameWidth":112,"frameHeight":112,"width":81,"height":81,"name":"attack000014","frameX":-17,"x":88},{"frameY":-17,"y":315,"frameWidth":112,"frameHeight":112,"width":85,"height":85,"name":"attack000015","frameX":-15,"x":1},{"frameY":-18,"y":225,"frameWidth":112,"frameHeight":112,"width":83,"height":83,"name":"attack000016","frameX":-16,"x":91},{"frameY":-15,"y":134,"frameWidth":112,"frameHeight":112,"width":89,"height":89,"name":"attack000017","frameX":-13,"x":1},{"frameY":-15,"y":225,"frameWidth":112,"frameHeight":112,"width":88,"height":88,"name":"attack000018","frameX":-13,"x":1},{"frameY":-23,"y":1,"frameWidth":112,"frameHeight":112,"width":73,"height":73,"name":"attack000019","frameX":-21,"x":404},{"frameY":-20,"y":401,"frameWidth":112,"frameHeight":112,"width":79,"height":79,"name":"attack000020","frameX":-18,"x":335},{"frameY":-17,"y":315,"frameWidth":112,"frameHeight":112,"width":84,"height":84,"name":"attack000021","frameX":-15,"x":88},{"frameY":-19,"y":401,"frameWidth":112,"frameHeight":112,"width":80,"height":80,"name":"attack000022","frameX":-17,"x":253},{"frameY":-17,"y":402,"frameWidth":112,"frameHeight":112,"width":85,"height":85,"name":"attack000023","frameX":-15,"x":1},{"frameY":-26,"y":1,"frameWidth":112,"frameHeight":112,"width":67,"height":67,"name":"attack000024","frameX":-24,"x":127},{"frameY":-24,"y":151,"frameWidth":112,"frameHeight":112,"width":71,"height":71,"name":"attack000025","frameX":-22,"x":404},{"frameY":-22,"y":310,"frameWidth":112,"frameHeight":112,"width":74,"height":74,"name":"attack000026","frameX":-20,"x":252},{"frameY":-21,"y":310,"frameWidth":112,"frameHeight":112,"width":76,"height":76,"name":"attack000027","frameX":-19,"x":174},{"frameY":-18,"y":134,"frameWidth":112,"frameHeight":112,"width":82,"height":82,"name":"attack000028","frameX":-16,"x":92},{"frameY":-19,"y":401,"frameWidth":112,"frameHeight":112,"width":80,"height":80,"name":"attack000029","frameX":-17,"x":171},{"frameY":-27,"y":1,"frameWidth":112,"frameHeight":112,"width":65,"height":65,"name":"attack000030","frameX":-25,"x":266},{"frameY":-25,"y":224,"frameWidth":112,"frameHeight":112,"width":69,"height":69,"name":"attack000031","frameX":-23,"x":404},{"frameY":-69,"y":1,"frameWidth":280,"frameHeight":280,"width":124,"height":131,"name":"刀光/daogaung1","frameX":-67,"x":1},{"frameY":0,"y":69,"frameWidth":68,"frameHeight":67,"width":68,"height":66,"name":"000005","frameX":0,"x":246},{"frameY":0,"y":1,"frameWidth":68,"frameHeight":67,"width":68,"height":66,"name":"000006","frameX":0,"x":196},{"frameY":0,"y":70,"frameWidth":68,"frameHeight":67,"width":68,"height":66,"name":"000007","frameX":0,"x":176},{"frameY":-6,"y":132,"frameWidth":68,"frameHeight":67,"width":58,"height":56,"name":"000008","frameX":-5,"x":316},{"frameY":-6,"y":138,"frameWidth":68,"frameHeight":67,"width":55,"height":55,"name":"000009","frameX":-6,"x":176},{"frameY":-7,"y":247,"frameWidth":68,"frameHeight":67,"width":53,"height":53,"name":"000010","frameX":-7,"x":303},{"frameY":-6,"y":190,"frameWidth":68,"frameHeight":67,"width":55,"height":55,"name":"000011","frameX":-6,"x":303},{"frameY":-26,"y":378,"frameWidth":68,"frameHeight":67,"width":16,"height":15,"name":"000012","frameX":-26,"x":457},{"frameY":-31,"y":301,"frameWidth":68,"frameHeight":67,"width":5,"height":5,"name":"000013","frameX":-31,"x":358}]}