{"width":1024,"SubTexture":[{"width":126,"y":280,"height":66,"name":"地影","x":250},{"width":213,"y":1,"height":277,"name":"111-1-切片描边-合并修片/zuochibang","x":250},{"width":181,"y":1,"height":241,"name":"111-1-切片描边-合并修片/youchibang","x":465},{"width":33,"y":403,"height":31,"name":"111-1-切片描边-合并修片/youxiaobi","x":1},{"width":25,"y":403,"height":24,"name":"111-1-切片描边-合并修片/youshou","x":91},{"width":247,"y":1,"height":400,"name":"111-1-切片描边-合并修片/wuqi","x":1},{"width":36,"y":375,"height":37,"name":"111-1-切片描边-合并修片/youshangbi","x":373},{"width":34,"y":348,"height":52,"name":"111-1-切片描边-合并修片/youdatui","x":306},{"width":27,"y":403,"height":26,"name":"111-1-切片描边-合并修片/youjiao","x":36},{"width":31,"y":402,"height":39,"name":"111-1-切片描边-合并修片/youxiaotui","x":291},{"width":60,"y":280,"height":93,"name":"111-1-切片描边-合并修片/shenti","x":378},{"width":36,"y":375,"height":37,"name":"111-1-切片描边-合并修片/zuoshangbi","x":411},{"width":24,"y":403,"height":28,"name":"111-1-切片描边-合并修片/zuojiao","x":65},{"width":26,"y":402,"height":41,"name":"111-1-切片描边-合并修片/zuoxiaotui","x":324},{"width":29,"y":348,"height":52,"name":"111-1-切片描边-合并修片/zuodatui","x":342},{"width":39,"y":397,"height":35,"name":"111-1-切片描边-合并修片/youjianbang","x":250},{"width":28,"y":434,"height":27,"name":"111-1-切片描边-合并修片/zuojiangbang-2","x":36},{"width":54,"y":348,"height":47,"name":"111-1-切片描边-合并修片/zuojiangbang-1","x":250},{"width":183,"y":244,"height":154,"name":"111-1-切片描边-合并修片/tou","x":465},{"width":33,"y":443,"height":31,"name":"111-1-切片描边-合并修片/zuoxiaobi","x":1},{"width":25,"y":433,"height":24,"name":"111-1-切片描边-合并修片/zuoshou","x":66}],"height":512,"name":"角色3","imagePath":"角色3_tex.png"}